echoss_s3handler/__init__.py
echoss_s3handler/echoss_logger.py
echoss_s3handler/s3_handler.py
echoss_s3handler-0.1.2.dist-info/METADATA
echoss_s3handler-0.1.2.dist-info/WHEEL
echoss_s3handler-0.1.2.dist-info/top_level.txt
echoss_s3handler-0.1.2.dist-info/RECORD
