Metadata-Version: 2.1
Name: echoss-s3handler
Version: 0.1.2
Summary: echoss AI Bigdata Solution - S3 handler
Home-page: 
Author: incheolshin
Author-email: incheolshin@12cm.co.kr
Keywords: echoss,echoss_s3handler,s3handler,s3_handler
Requires-Python: >3.7
Requires-Dist: boto3 (~=1.19.0)
Requires-Dist: opencv-python (==4.8.0.74)
Requires-Dist: tqdm (==4.63.2)
Requires-Dist: pillow (==10.1.0)
